codexen/__init__.py
codexen/foo.py
codexen-0.0.0.dist-info/LICENSE
codexen-0.0.0.dist-info/METADATA
codexen-0.0.0.dist-info/WHEEL
codexen-0.0.0.dist-info/top_level.txt
codexen-0.0.0.dist-info/RECORD
