Metadata-Version: 2.1
Name: codexen
Version: 0.0.0
Summary: Code Execution Engine
Author-email: Harsh Verma <synacktra.work@gmail.com>
Project-URL: Documentation, https://synacktraa.github.io/codexen/
Project-URL: Homepage, https://synacktraa.github.io/codexen/
Project-URL: Repository, https://github.com/synacktraa/codexen
Keywords: python
Classifier: Intended Audience :: Developers
Classifier: Programming Language :: Python
Classifier: Programming Language :: Python :: 3
Classifier: Programming Language :: Python :: 3.9
Classifier: Programming Language :: Python :: 3.10
Classifier: Programming Language :: Python :: 3.11
Classifier: Programming Language :: Python :: 3.12
Classifier: Programming Language :: Python :: 3.13
Classifier: Topic :: Software Development :: Libraries :: Python Modules
Requires-Python: <4.0,>=3.9
License-File: LICENSE
